yywtestpackage/__init__ .py
yywtestpackage/core.py
yywtestpackage/myfunction.py
yywtestpackage-0.1.4.dist-info/LICENSE.txt
yywtestpackage-0.1.4.dist-info/METADATA
yywtestpackage-0.1.4.dist-info/WHEEL
yywtestpackage-0.1.4.dist-info/top_level.txt
yywtestpackage-0.1.4.dist-info/RECORD
